README.md
setup.py
example_pkg_vegacandle3.egg-info/PKG-INFO
example_pkg_vegacandle3.egg-info/SOURCES.txt
example_pkg_vegacandle3.egg-info/dependency_links.txt
example_pkg_vegacandle3.egg-info/top_level.txt
vegacandle3/__init__.py
vegacandle3/addfunc.py