Metadata-Version: 2.1
Name: example-pkg-vegacandle3
Version: 0.1.1
Summary: [in description] A small example package
Home-page: https://github.com/pypa/sampleproject
Author: NA Author
Author-email: author@example.com
License: UNKNOWN
Platform: UNKNOWN
Classifier: Programming Language :: Python :: 3
Classifier: License :: OSI Approved :: MIT License
Classifier: Operating System :: OS Independent
Requires-Python: >=3.6
